LICENSE
MANIFEST.in
README.txt
setup.py
atomisator/__init__.py
atomisator.outputs.egg-info/PKG-INFO
atomisator.outputs.egg-info/SOURCES.txt
atomisator.outputs.egg-info/dependency_links.txt
atomisator.outputs.egg-info/entry_points.txt
atomisator.outputs.egg-info/namespace_packages.txt
atomisator.outputs.egg-info/not-zip-safe
atomisator.outputs.egg-info/requires.txt
atomisator.outputs.egg-info/top_level.txt
atomisator/outputs/__init__.py
atomisator/outputs/mail.py
atomisator/outputs/docs/README.txt
atomisator/outputs/tests/__init__.py
atomisator/outputs/tests/test_mail.py